CHANGELOG.rst
INSTALL.rst
ISSUES.rst
MANIFEST.in
README.rst
TODO.rst
buildout.cfg
setup.py
test.cfg
src/repoze/__init__.py
src/repoze.who.plugins.cas.egg-info/PKG-INFO
src/repoze.who.plugins.cas.egg-info/SOURCES.txt
src/repoze.who.plugins.cas.egg-info/dependency_links.txt
src/repoze.who.plugins.cas.egg-info/namespace_packages.txt
src/repoze.who.plugins.cas.egg-info/not-zip-safe
src/repoze.who.plugins.cas.egg-info/requires.txt
src/repoze.who.plugins.cas.egg-info/top_level.txt
src/repoze/who/__init__.py
src/repoze/who/plugins/__init__.py
src/repoze/who/plugins/cas/__init__.py
src/repoze/who/plugins/cas/challenge_decider.py
src/repoze/who/plugins/cas/main_plugin.py
src/repoze/who/plugins/cas/tests/__init__.py
src/repoze/who/plugins/cas/tests/challenge_decider_test.py
src/repoze/who/plugins/cas/tests/handler.py
src/repoze/who/plugins/cas/tests/main_plugin_test.py
src/repoze/who/plugins/cas/tests/test_src.py