Metadata-Version: 1.1
Name: repoze.who.plugins.cas
Version: 0.2.1
Summary: CAS plugin for repoze.who by Makina Corpus
Home-page: http://github.com/kiorky/repoze.who.plugins.cas/
Author: Simon Thepot, Mathieu Pasquet
Author-email: dj.coin@laposte.net, kiorky@cryptelium.net
License: BSD
Keywords: cas authentication server web wsgi repoze repoze.who sponsorised by Makina Corpus
Platform: UNKNOWN
Classifier: Development Status :: 2 - Pre-Alpha
Classifier: Intended Audience :: Developers
Classifier: License :: OSI Approved :: BSD License
Classifier: Natural Language :: English
Classifier: Operating System :: OS Independent
Classifier: Programming Language :: Python
Classifier: Topic :: Internet :: WWW/HTTP :: WSGI :: Middleware
Classifier: Topic :: System :: Systems Administration :: Authentication/Directory
